xmi_logger/__init__.py
xmi_logger/__version__.py
xmi_logger/advanced_features.py
xmi_logger/xmi_logger.py
xmi_logger-0.0.7.dist-info/METADATA
xmi_logger-0.0.7.dist-info/WHEEL
xmi_logger-0.0.7.dist-info/top_level.txt
xmi_logger-0.0.7.dist-info/RECORD
