Metadata-Version: 2.4
Name: xmi_logger
Version: 0.0.7
Summary: An enhanced logger based on Loguru
Home-page: https://github.com/wang-zhibo/xmi_logger
Author: gm.zhibo.wang
Author-email: gm.zhibo.wang@gmail.com
Project-URL: Bug Reports, https://github.com/wang-zhibo/xmi_logger/issues
Project-URL: Source, https://github.com/wang-zhibo/xmi_logger
Classifier: Programming Language :: Python :: 3
Classifier: Operating System :: OS Independent
Requires-Python: >=3.6
Requires-Dist: loguru==0.7.3
Requires-Dist: requests
Requires-Dist: aiohttp
Dynamic: author
Dynamic: author-email
Dynamic: classifier
Dynamic: description
Dynamic: description-content-type
Dynamic: home-page
Dynamic: project-url
Dynamic: requires-dist
Dynamic: requires-python
Dynamic: summary
